langconv/__init__.py
langconv/converter.py
langconv/data/zh/CN.json
langconv/data/zh/HK.json
langconv/data/zh/LICENSE.md
langconv/data/zh/TW.json
langconv/data/zh/hans.json
langconv/data/zh/hant.json
langconv/language/__init__.py
langconv/language/zh.py
langconv/trie.py
langconv-0.3.0.dist-info/LICENSE
langconv-0.3.0.dist-info/METADATA
langconv-0.3.0.dist-info/WHEEL
langconv-0.3.0.dist-info/RECORD
