Metadata-Version: 2.1
Name: langconv
Version: 0.3.0
Summary: A Python library for conversion between Traditional and Simplified Chinese, inspired by MediaWiki's LanguageConverter.
Home-page: https://github.com/Teahouse-Studios/langconv.py
License: MIT
Author: Dianliang233
Author-email: dianliang233@gmail.com
Requires-Python: >=3.9,<4.0
Classifier: Development Status :: 4 - Beta
Classifier: Intended Audience :: Developers
Classifier: Intended Audience :: Education
Classifier: Intended Audience :: Science/Research
Classifier: License :: OSI Approved :: MIT License
Classifier: Natural Language :: Chinese (Simplified)
Classifier: Natural Language :: Chinese (Traditional)
Classifier: Programming Language :: Python :: 3
Classifier: Programming Language :: Python :: 3.9
Classifier: Programming Language :: Python :: 3.10
Classifier: Programming Language :: Python :: 3.11
Classifier: Programming Language :: Python :: 3.12
Classifier: Topic :: Scientific/Engineering
Classifier: Topic :: Software Development :: Internationalization
Classifier: Topic :: Software Development :: Libraries :: Python Modules
Classifier: Topic :: Software Development :: Localization
Classifier: Topic :: Text Processing :: Linguistic
Classifier: Typing :: Typed
Requires-Dist: attrs (>=23.2.0,<24.0.0)
Requires-Dist: iso639-lang (>=2.2.3,<3.0.0)
Project-URL: Repository, https://github.com/Teahouse-Studios/langconv.py
